LICENSE
MANIFEST.in
README.md
setup.py
mdvis/__init__.py
mdvis/server.py
mdvis.egg-info/PKG-INFO
mdvis.egg-info/SOURCES.txt
mdvis.egg-info/dependency_links.txt
mdvis.egg-info/entry_points.txt
mdvis.egg-info/not-zip-safe
mdvis.egg-info/requires.txt
mdvis.egg-info/top_level.txt
mdvis/static/base.css
mdvis/static/md-style.css
mdvis/templates/document.html
mdvis/templates/index.html