Metadata-Version: 1.1
Name: mdvis
Version: 0.1.1
Summary: Simple way to read folders of mardown files on the browser
Home-page: https://github.com/dethos/mdvis
Author: Gonçalo Valério
Author-email: gon@ovalerio.net
License: GPLv3
Platform: UNKNOWN
Classifier: Topic :: Documentation
Classifier: Topic :: Internet :: WWW/HTTP
Classifier: Topic :: Text Processing :: Markup
Classifier: Programming Language :: Python :: 3
Classifier: License :: OSI Approved :: GNU General Public License v3 (GPLv3)
